antfyutils/__init__.py
antfyutils/data_obj.py
antfyutils/format.py
antfyutils/obj.py
antfyutils/push_utils.py
antfyutils-0.0.7.dist-info/METADATA
antfyutils-0.0.7.dist-info/WHEEL
antfyutils-0.0.7.dist-info/top_level.txt
antfyutils-0.0.7.dist-info/RECORD
