Metadata-Version: 2.1
Name: antfyutils
Version: 0.0.7
License: GPLv3
Requires-Python: >=3.8
Requires-Dist: aiohttp
Requires-Dist: dataclasses-json
Requires-Dist: toml-dataclass
